AUTHORS.md
LICENSE.md
README.rst
setup.py
src/redfish_advantech/__init__.py
src/redfish_advantech.egg-info/PKG-INFO
src/redfish_advantech.egg-info/SOURCES.txt
src/redfish_advantech.egg-info/dependency_links.txt
src/redfish_advantech.egg-info/requires.txt
src/redfish_advantech.egg-info/top_level.txt
src/redfish_advantech/discovery/__init__.py
src/redfish_advantech/discovery/discovery.py
src/redfish_advantech/restful/__init__.py
src/redfish_advantech/restful/v1.py
src/redfish_advantech/restful/v1api.py
src/redfish_advantech/restful/v1api拷貝.py