Metadata-Version: 2.1
Name: redfish-advantech
Version: 0.3.0
Summary: Advantech Redfish Python Library
Home-page: https://github.com/chhuang789/redfish_advantech
Author: C.H. Huang (Just for test so far)
Author-email: chhuang789@gmail.com
License: BSD 3-clause "New" or "Revised License"
Keywords: Redfish
Platform: UNKNOWN
Classifier: Development Status :: 5 - Production/Stable
Classifier: License :: OSI Approved :: BSD License
Classifier: Programming Language :: Python :: 3
Classifier: Topic :: Communications
License-File: LICENSE.md
License-File: AUTHORS.md
